mysql/__init__.py
mysql/runtime.py
mysql/tool.py
opsmate_tool_mysql-0.1.2a0.dist-info/METADATA
opsmate_tool_mysql-0.1.2a0.dist-info/WHEEL
opsmate_tool_mysql-0.1.2a0.dist-info/entry_points.txt
opsmate_tool_mysql-0.1.2a0.dist-info/licenses/LICENSE
opsmate_tool_mysql-0.1.2a0.dist-info/RECORD
