Metadata-Version: 2.4
Name: opsmate-tool-mysql
Version: 0.1.2a0
Summary: MySQL tool for opsmate
Author-email: Jingkai He <jingkai@hey.com>
License: MIT License
License-File: LICENSE
Requires-Python: <4.0,>=3.10
Requires-Dist: opsmate
Requires-Dist: pymysql[rsa]
